django_lti_auth/__init__.py
django_lti_auth/urls.py
django_lti_auth/views.py
django_lti_auth/templates/denied.html
django_lti_auth-1.0.0.dist-info/LICENSE
django_lti_auth-1.0.0.dist-info/METADATA
django_lti_auth-1.0.0.dist-info/WHEEL
django_lti_auth-1.0.0.dist-info/top_level.txt
django_lti_auth-1.0.0.dist-info/RECORD
