Metadata-Version: 2.1
Name: django-lti-auth
Version: 1.0.0
Summary: Django LTI Authentication Made Easy. Easily integrate with your LTI provider for django projects
Home-page: https://github.com/rohitjose/django-lti-auth.git
Author: : Rohit Jose
Author-email: : rohitjose@gmail.com
License: MIT
Platform: UNKNOWN
Classifier: Development Status :: 3 - Alpha
Classifier: Intended Audience :: Developers
Classifier: Topic :: Software Development :: Libraries :: Python Modules
Classifier: License :: OSI Approved :: MIT License
Classifier: Framework :: Django :: 2.0
Classifier: Framework :: Django :: 2.1
Classifier: Programming Language :: Python :: 3
Classifier: Programming Language :: Python :: 3.4
Classifier: Programming Language :: Python :: 3.5
Classifier: Programming Language :: Python :: 3.6
Classifier: Programming Language :: Python :: 3.7
Requires-Dist: PyLTI (==0.5.1)
